MutationChecker/__init__.py
MutationChecker/dip.py
MutationChecker/embl.py
MutationChecker/mapper.py
MutationChecker/prosite.py
MutationChecker/structure.py
MutationChecker-0.1.7.dist-info/LICENCE
MutationChecker-0.1.7.dist-info/METADATA
MutationChecker-0.1.7.dist-info/WHEEL
MutationChecker-0.1.7.dist-info/top_level.txt
MutationChecker-0.1.7.dist-info/RECORD
