Metadata-Version: 2.1
Name: MutationChecker
Version: 0.1.7
Summary: Package for the computation of distances from a residue to the catalytic active residues.
Home-page: UNKNOWN
Author: RMolina
Author-email: ruben.molina-fernandez@upf.edu
License: UNKNOWN
Platform: UNKNOWN
Classifier: Programming Language :: Python :: 3
Classifier: Programming Language :: Python :: 3.6
Classifier: Programming Language :: Python :: 3.7
Classifier: Programming Language :: Python :: 3.8
